PS_Validation/Config.txt
PS_Validation/ConnectOracledb.py
PS_Validation/FinalDecision.py
PS_Validation/ParsePDF.py
PS_Validation/TablesData.py
PS_Validation/TablesQuery.py
PS_Validation/Validation.py
PS_Validation/__init__.py
PS_Validation/read_file.py
PS_Validation/instantclient/BASIC_LITE_LICENSE
PS_Validation/instantclient/BASIC_LITE_README
PS_Validation/instantclient/adrci.exe
PS_Validation/instantclient/adrci.sym
PS_Validation/instantclient/genezi.exe
PS_Validation/instantclient/genezi.sym
PS_Validation/instantclient/oci.dll
PS_Validation/instantclient/oci.sym
PS_Validation/instantclient/ocijdbc21.dll
PS_Validation/instantclient/ocijdbc21.sym
PS_Validation/instantclient/ociw32.dll
PS_Validation/instantclient/ociw32.sym
PS_Validation/instantclient/ojdbc8.jar
PS_Validation/instantclient/orannzsbb.dll
PS_Validation/instantclient/orannzsbb.sym
PS_Validation/instantclient/oraocci21.dll
PS_Validation/instantclient/oraocci21.sym
PS_Validation/instantclient/oraocci21d.dll
PS_Validation/instantclient/oraocci21d.sym
PS_Validation/instantclient/oraociicus.dll
PS_Validation/instantclient/oraociicus.sym
PS_Validation/instantclient/orasql.dll
PS_Validation/instantclient/orasql.sym
PS_Validation/instantclient/stat_df.csv
PS_Validation/instantclient/ucp.jar
PS_Validation/instantclient/uidrvci.exe
PS_Validation/instantclient/uidrvci.sym
PS_Validation/instantclient/xstreams.jar
PS_Validation/instantclient/network/admin/README
PS_Validation-1.0.7.dist-info/METADATA
PS_Validation-1.0.7.dist-info/WHEEL
PS_Validation-1.0.7.dist-info/top_level.txt
PS_Validation-1.0.7.dist-info/RECORD
