Metadata-Version: 2.1
Name: PS_Validation
Version: 1.0.7
Summary: PS_Validation Project
Home-page: https://github.com/HamdEmad/ps-validation-project/tree/main/PS_Validation
Author: Hamdi Emad
Author-email: hamdy1721998@gmail.com
